farsante/__init__.py
farsante/dask_dfs.py
farsante/dask_generators.py
farsante/pandas_dfs.py
farsante/pandas_generators.py
farsante/pyspark_dfs.py
farsante/pyspark_generators.py
farsante-0.2.0.dist-info/WHEEL
farsante-0.2.0.dist-info/METADATA
farsante-0.2.0.dist-info/RECORD
