Metadata-Version: 2.1
Name: farsante
Version: 0.2.0
Summary: Fake DataFrame generators for Pandas and PySpark
Author: MrPowers
Author-email: matthewkevinpowers@gmail.com
Requires-Python: >=3.6.1
Classifier: Programming Language :: Python :: 3
Classifier: Programming Language :: Python :: 3.7
Classifier: Programming Language :: Python :: 3.8
Requires-Dist: dask[dataframe] (>=2.23.0,<3.0.0)
Requires-Dist: mimesis (>=4.0.0,<5.0.0)
Requires-Dist: pandas (>=1.0.0)
Requires-Dist: pyspark (>=2.0.0)
